rtl/counter.vhd
--+--------------------------------------------------------------------------------------------------------------------+
--|  File: counter.vhd
--|  Project: counter
--|  Description: Example of counter with asynchronous reset and synchronous enable.
--|
--+--------------------------------------------------------------------------------------------------------------------+
--+-----------------------------------------------------------------------------+
--|									LIBRARIES									|
--+-----------------------------------------------------------------------------+
library ieee;
use ieee.std_logic_1164.all;
use ieee.std_logic_unsigned.all;
use ieee.std_logic_arith.all;

--+-----------------------------------------------------------------------------+
--|								ENTITY & ARCHITECTURE							|
--+-----------------------------------------------------------------------------+
entity counter is
	generic(size : integer := 8);
port (
	clk_i  : in std_logic;
	arst_i : in std_logic;
    en_i   : in std_logic;
   	q_o    : out std_logic_vector(size-1 downto 0)
);
end counter;

architecture rtl of counter is
    --+-----------------------------------------------------------------------------+
    --|									SIGNALS   									|
    --+-----------------------------------------------------------------------------+
begin
	CNT_P: process(clk_i, arst_i, en_i)
        variable iq : std_logic_vector(size-1 downto 0) := (others => '0');
	begin
	    if (arst_i = '1') then
    		iq := (others => '0');
        elsif (rising_edge(clk_i)) then
            if (en_i = '1') then
                iq := iq + 1;
            end if;
    	end if;
        q_o <= iq;
    end process CNT_P;
end rtl;

tb/tb_counter.vhd
--+--------------------------------------------------------------------------------------------------------------------+
--|  File: tb_counter.vhd
--|  Project: counter
--|  Description: Test bench for counter module.
--|
--+--------------------------------------------------------------------------------------------------------------------+
--+-----------------------------------------------------------------------------+
--|									LIBRARIES									|
--+-----------------------------------------------------------------------------+
library ieee;
use ieee.std_logic_1164.all;
use ieee.std_logic_unsigned.all;
--
use std.textio.all;
use ieee.std_logic_textio.all;

--+-----------------------------------------------------------------------------+
--|									ENTITY   									|
--+-----------------------------------------------------------------------------+
entity tb_counter is
end tb_counter;

architecture behavior of tb_counter is
--+-----------------------------------------------------------------------------+
--|									COMPONENTS									|
--+-----------------------------------------------------------------------------+
--+-----------------------------------------------------------------------------+
--|									SIGNALS   									|
--+-----------------------------------------------------------------------------+
    -- cnt_upld/cnt_dwld
    signal clk    : std_logic := '0';
    signal rst    : std_logic := '0';
    signal enable : std_logic := '0';
    signal q      : std_logic_vector(7 downto 0) := (others => '0');

    procedure printmsg(msg : string) is
		variable l : line;
	begin
        write(l, msg);
        writeline(output, l);
	end printmsg;

begin
    --+-------------------------------------------------------------------------+
    --|  DUT: Component instances												|
    --+-------------------------------------------------------------------------+
    u0: entity work.counter
        generic map(size => 8)
    port map (
        clk_i  => clk,
        arst_i => rst,
        en_i   => enable,
        q_o    => q
    );

    --+-----------------------------------------+
	--|  RST/LD/ENABLE         					|
	--+-----------------------------------------+
    rst_P: process
        variable l1 : line;
    begin
        write(l1, string'("Start Simulation"));
        writeline(output, l1);
        wait for 100 ns;
        printmsg("Set Reset");
        rst <= '1';
        enable <= '0';
        wait for 100 ns;
        printmsg("Clear Reset");
        rst <= '0';
        wait for 100 ns;
        printmsg("Enable count");
        enable <= '1';
        printmsg("End rst process");
        wait;
    end process rst_P;

    --+-----------------------------------------+
	--|  CLK                   					|
	--+-----------------------------------------+
    clk_P: process
    begin
        printmsg("Start Clock");
        clk_l: for i in 0 to 100 loop
            clk <= '0';
            wait for 20 ns;
            clk <= '1';
            wait for 20 ns;
        end loop clk_l;
        printmsg("End Clock process");
        wait;
    end process clk_P;

end behavior;

sim/tb_counter.vcd
$date
  Thu Oct 28 11:02:42 2021
$end
$version
  GHDL v0
$end
$timescale
  1 fs
$end
$scope module standard $end
$upscope $end
$scope module textio $end
$upscope $end
$scope module std_logic_1164 $end
$upscope $end
$scope module std_logic_arith $end
$upscope $end
$scope module std_logic_unsigned $end
$upscope $end
$scope module std_logic_textio $end
$upscope $end
$scope module tb_counter $end
$var reg 1 ! clk $end
$var reg 1 " rst $end
$var reg 1 # enable $end
$var reg 8 $ q[7:0] $end
$scope module u0 $end
$var reg 1 % clk_i $end
$var reg 1 & arst_i $end
$var reg 1 ' en_i $end
$var reg 8 ( q_o[7:0] $end
$upscope $end
$upscope $end
$enddefinitions $end
#0
0!
0"
0#
b00000000 $
0%
0&
0'
b00000000 (
#20000000
1!
1%
#40000000
0!
0%
#60000000
1!
1%
#80000000
0!
0%
#100000000
1!
1"
1%
1&
#120000000
0!
0%
#140000000
1!
1%
#160000000
0!
0%
#180000000
1!
1%
#200000000
0!
0"
0%
0&
#220000000
1!
1%
#240000000
0!
0%
#260000000
1!
1%
#280000000
0!
0%
#300000000
1!
1#
b00000001 $
1%
1'
b00000001 (
#320000000
0!
0%
#340000000
1!
b00000010 $
1%
b00000010 (
#360000000
0!
0%
#380000000
1!
b00000011 $
1%
b00000011 (
#400000000
0!
0%
#420000000
1!
b00000100 $
1%
b00000100 (
#440000000
0!
0%
#460000000
1!
b00000101 $
1%
b00000101 (
#480000000
0!
0%
#500000000
1!
b00000110 $
1%
b00000110 (
#520000000
0!
0%
#540000000
1!
b00000111 $
1%
b00000111 (
#560000000
0!
0%
#580000000
1!
b00001000 $
1%
b00001000 (
#600000000
0!
0%
#620000000
1!
b00001001 $
1%
b00001001 (
#640000000
0!
0%
#660000000
1!
b00001010 $
1%
b00001010 (
#680000000
0!
0%
#700000000
1!
b00001011 $
1%
b00001011 (
#720000000
0!
0%
#740000000
1!
b00001100 $
1%
b00001100 (
#760000000
0!
0%
#780000000
1!
b00001101 $
1%
b00001101 (
#800000000
0!
0%
#820000000
1!
b00001110 $
1%
b00001110 (
#840000000
0!
0%
#860000000
1!
b00001111 $
1%
b00001111 (
#880000000
0!
0%
#900000000
1!
b00010000 $
1%
b00010000 (
#920000000
0!
0%
#940000000
1!
b00010001 $
1%
b00010001 (
#960000000
0!
0%
#980000000
1!
b00010010 $
1%
b00010010 (
#1000000000
0!
0%
#1020000000
1!
b00010011 $
1%
b00010011 (
#1040000000
0!
0%
#1060000000
1!
b00010100 $
1%
b00010100 (
#1080000000
0!
0%
#1100000000
1!
b00010101 $
1%
b00010101 (
#1120000000
0!
0%
#1140000000
1!
b00010110 $
1%
b00010110 (
#1160000000
0!
0%
#1180000000
1!
b00010111 $
1%
b00010111 (
#1200000000
0!
0%
#1220000000
1!
b00011000 $
1%
b00011000 (
#1240000000
0!
0%
#1260000000
1!
b00011001 $
1%
b00011001 (
#1280000000
0!
0%
#1300000000
1!
b00011010 $
1%
b00011010 (
#1320000000
0!
0%
#1340000000
1!
b00011011 $
1%
b00011011 (
#1360000000
0!
0%
#1380000000
1!
b00011100 $
1%
b00011100 (
#1400000000
0!
0%
#1420000000
1!
b00011101 $
1%
b00011101 (
#1440000000
0!
0%
#1460000000
1!
b00011110 $
1%
b00011110 (
#1480000000
0!
0%
#1500000000
1!
b00011111 $
1%
b00011111 (
#1520000000
0!
0%
#1540000000
1!
b00100000 $
1%
b00100000 (
#1560000000
0!
0%
#1580000000
1!
b00100001 $
1%
b00100001 (
#1600000000
0!
0%
#1620000000
1!
b00100010 $
1%
b00100010 (
#1640000000
0!
0%
#1660000000
1!
b00100011 $
1%
b00100011 (
#1680000000
0!
0%
#1700000000
1!
b00100100 $
1%
b00100100 (
#1720000000
0!
0%
#1740000000
1!
b00100101 $
1%
b00100101 (
#1760000000
0!
0%
#1780000000
1!
b00100110 $
1%
b00100110 (
#1800000000
0!
0%
#1820000000
1!
b00100111 $
1%
b00100111 (
#1840000000
0!
0%
#1860000000
1!
b00101000 $
1%
b00101000 (
#1880000000
0!
0%
#1900000000
1!
b00101001 $
1%
b00101001 (
#1920000000
0!
0%
#1940000000
1!
b00101010 $
1%
b00101010 (
#1960000000
0!
0%
#1980000000
1!
b00101011 $
1%
b00101011 (
#2000000000
0!
0%
#2020000000
1!
b00101100 $
1%
b00101100 (
#2040000000
0!
0%
#2060000000
1!
b00101101 $
1%
b00101101 (
#2080000000
0!
0%
#2100000000
1!
b00101110 $
1%
b00101110 (
#2120000000
0!
0%
#2140000000
1!
b00101111 $
1%
b00101111 (
#2160000000
0!
0%
#2180000000
1!
b00110000 $
1%
b00110000 (
#2200000000
0!
0%
#2220000000
1!
b00110001 $
1%
b00110001 (
#2240000000
0!
0%
#2260000000
1!
b00110010 $
1%
b00110010 (
#2280000000
0!
0%
#2300000000
1!
b00110011 $
1%
b00110011 (
#2320000000
0!
0%
#2340000000
1!
b00110100 $
1%
b00110100 (
#2360000000
0!
0%
#2380000000
1!
b00110101 $
1%
b00110101 (
#2400000000
0!
0%
#2420000000
1!
b00110110 $
1%
b00110110 (
#2440000000
0!
0%
#2460000000
1!
b00110111 $
1%
b00110111 (
#2480000000
0!
0%
#2500000000
1!
b00111000 $
1%
b00111000 (
#2520000000
0!
0%
#2540000000
1!
b00111001 $
1%
b00111001 (
#2560000000
0!
0%
#2580000000
1!
b00111010 $
1%
b00111010 (
#2600000000
0!
0%
#2620000000
1!
b00111011 $
1%
b00111011 (
#2640000000
0!
0%
#2660000000
1!
b00111100 $
1%
b00111100 (
#2680000000
0!
0%
#2700000000
1!
b00111101 $
1%
b00111101 (
#2720000000
0!
0%
#2740000000
1!
b00111110 $
1%
b00111110 (
#2760000000
0!
0%
#2780000000
1!
b00111111 $
1%
b00111111 (
#2800000000
0!
0%
#2820000000
1!
b01000000 $
1%
b01000000 (
#2840000000
0!
0%
#2860000000
1!
b01000001 $
1%
b01000001 (
#2880000000
0!
0%
#2900000000
1!
b01000010 $
1%
b01000010 (
#2920000000
0!
0%
#2940000000
1!
b01000011 $
1%
b01000011 (
#2960000000
0!
0%
#2980000000
1!
b01000100 $
1%
b01000100 (
#3000000000
0!
0%
#3020000000
1!
b01000101 $
1%
b01000101 (
#3040000000
0!
0%
#3060000000
1!
b01000110 $
1%
b01000110 (
#3080000000
0!
0%
#3100000000
1!
b01000111 $
1%
b01000111 (
#3120000000
0!
0%
#3140000000
1!
b01001000 $
1%
b01001000 (
#3160000000
0!
0%
#3180000000
1!
b01001001 $
1%
b01001001 (
#3200000000
0!
0%
#3220000000
1!
b01001010 $
1%
b01001010 (
#3240000000
0!
0%
#3260000000
1!
b01001011 $
1%
b01001011 (
#3280000000
0!
0%
#3300000000
1!
b01001100 $
1%
b01001100 (
#3320000000
0!
0%
#3340000000
1!
b01001101 $
1%
b01001101 (
#3360000000
0!
0%
#3380000000
1!
b01001110 $
1%
b01001110 (
#3400000000
0!
0%
#3420000000
1!
b01001111 $
1%
b01001111 (
#3440000000
0!
0%
#3460000000
1!
b01010000 $
1%
b01010000 (
#3480000000
0!
0%
#3500000000
1!
b01010001 $
1%
b01010001 (
#3520000000
0!
0%
#3540000000
1!
b01010010 $
1%
b01010010 (
#3560000000
0!
0%
#3580000000
1!
b01010011 $
1%
b01010011 (
#3600000000
0!
0%
#3620000000
1!
b01010100 $
1%
b01010100 (
#3640000000
0!
0%
#3660000000
1!
b01010101 $
1%
b01010101 (
#3680000000
0!
0%
#3700000000
1!
b01010110 $
1%
b01010110 (
#3720000000
0!
0%
#3740000000
1!
b01010111 $
1%
b01010111 (
#3760000000
0!
0%
#3780000000
1!
b01011000 $
1%
b01011000 (
#3800000000
0!
0%
#3820000000
1!
b01011001 $
1%
b01011001 (
#3840000000
0!
0%
#3860000000
1!
b01011010 $
1%
b01011010 (
#3880000000
0!
0%
#3900000000
1!
b01011011 $
1%
b01011011 (
#3920000000
0!
0%
#3940000000
1!
b01011100 $
1%
b01011100 (
#3960000000
0!
0%
#3980000000
1!
b01011101 $
1%
b01011101 (
#4000000000
0!
0%
#4020000000
1!
b01011110 $
1%
b01011110 (
